.gitignore
.travis.yml
CHANGES.md
LICENSE
MANIFEST.in
README.md
TODO.md
req.txt
setup.py
tox.ini
spark_optimizer/__init__.py
spark_optimizer/cli.py
spark_optimizer/emr_instance.yaml
spark_optimizer/emr_update.py
spark_optimizer/optimizer.py
spark_optimizer.egg-info/PKG-INFO
spark_optimizer.egg-info/SOURCES.txt
spark_optimizer.egg-info/dependency_links.txt
spark_optimizer.egg-info/entry_points.txt
spark_optimizer.egg-info/not-zip-safe
spark_optimizer.egg-info/requires.txt
spark_optimizer.egg-info/top_level.txt
test/__init__.py
test/test_cli.py
test/test_optimizer.py