Metadata-Version: 2.1
Name: spark-optimizer
Version: 0.1.8
Summary: Optimize AWS EMR spark settings (spark-config-cheatsheet)
Home-page: https://github.com/delijati/spark-optimizer
Author: Josip Delic
Author-email: delijati@gmx.net
License: MIT
Keywords: spark emr aws cluster yarn
Platform: UNKNOWN
Classifier: Development Status :: 4 - Beta
Classifier: Environment :: Console
Classifier: Intended Audience :: Developers
Classifier: License :: OSI Approved :: MIT License
Classifier: Natural Language :: English
Classifier: Programming Language :: Python :: 3
Classifier: Programming Language :: Python :: 3.5
Classifier: Programming Language :: Python :: 3.6
